{
    "sourceFile": "README.md",
    "activeCommit": 0,
    "commits": [
        {
            "activePatchIndex": 6,
            "patches": [
                {
                    "date": 1763982588127,
                    "content": "Index: \n===================================================================\n--- \n+++ \n"
                },
                {
                    "date": 1764023821857,
                    "content": "Index: \n===================================================================\n--- \n+++ \n@@ -1,27 +1,466 @@\n-# Giga LAN Manager\r\n+# ðŸŽ® GIGA LAN Tournament Manager\r\n \r\n-## Project Overview\r\n-A self-hosted web application for managing LAN party tournaments with a Swiss-lite group stage and Double-House playoffs. Supports group phases, scoring, and interactive brackets.\r\n+A modern, self-hosted web application for managing competitive LAN party tournaments with an immersive gaming aesthetic. Features a Swiss-lite group stage system and single-elimination playoffs with interactive bracket management.\r\n \r\n-## Tech Stack\r\n-- Frontend: Svelte (Vite) + Tailwind CSS\r\n-- Backend: Node.js (Express) + TypeScript\r\n-- Database: Redis\r\n-- Infrastructure: Docker & Docker Compose\r\n+![Tournament Manager Preview](https://via.placeholder.com/800x400/0a0e27/00ff88?text=GIGA+LAN+Tournament+Manager)\r\n \r\n-## Folder Structure\r\n-- `server/`: Backend logic, tournament management, API endpoints\r\n-- `src/`: Frontend Svelte components, pages, API client\r\n-- `public/`: Static assets\r\n-- `tests/`: Test files (e.g., brackets.test.ts)\r\n-- Root files: package.json, docker-compose.yml, vite.config.ts, etc.\r\n+## âœ¨ Features\r\n \r\n-## Getting Started\r\n-See detailed instructions in this file or run with Docker: `docker compose up --build`\r\n+### ðŸ† Tournament Management\r\n+- **Multi-Tournament Support**: Create and manage multiple tournaments simultaneously\r\n+- **Real-time State Management**: Live updates of tournament progress and standings\r\n+- **Tournament Completion**: Automatic completion detection with celebration podium\r\n \r\n-## Usage\r\n-1. Registration: Add players on home page\r\n-2. Start Group Stage: Once >=4 players\r\n-3. Groups: Enter points for matches\r\n-4. Brackets: Generate and advance winners\r\n+### ðŸ‘¥ Player Management\r\n+- **Dynamic Registration**: Add players during registration phase\r\n+- **Player Name Editing**: Edit player names throughout tournament (with restrictions)\r\n+- **Live Standings**: Real-time player statistics and rankings\r\n \r\n+### ðŸŽ¯ Group Stage (Swiss-lite)\r\n+- **Automated Pod Generation**: Smart grouping based on player count\r\n+- **Round-Robin Matches**: Complete round-robin within each group\r\n+- **Flexible Scoring**: Win (3pts), Draw (1pt), Loss (0pts)\r\n+- **Group Name Customization**: Edit group names during registration\r\n+- **Match Result Submission**: Interactive result entry with validation\r\n+\r\n+### ðŸ… Playoffs & Brackets\r\n+- **Single Elimination**: Traditional bracket format\r\n+- **Interactive Advancement**: Click-to-advance bracket system\r\n+- **Multiple Bracket Sizes**: 4, 6, or 8 player playoffs\r\n+- **3rd Place Matches**: Consolation bracket for comprehensive placement\r\n+- **Champion Celebration**: Immersive podium with trophy and confetti effects\r\n+\r\n+### ðŸŽ¨ User Experience\r\n+- **Gaming Aesthetic**: Cyberpunk-inspired dark theme with neon accents\r\n+- **Responsive Design**: Works on desktop, tablet, and mobile devices\r\n+- **Smooth Animations**: Card entrance effects and hover transitions\r\n+- **Accessibility**: Keyboard navigation and screen reader support\r\n+\r\n+## ðŸ—ï¸ Architecture & Tech Stack\r\n+\r\n+### Frontend\r\n+- **Framework**: Svelte 5 with modern reactivity (`$state`, `$derived`, `$effect`)\r\n+- **Build Tool**: Vite for fast development and optimized production builds\r\n+- **Styling**: Tailwind CSS with custom gaming-themed design system\r\n+- **Icons**: Heroicons and custom SVG graphics\r\n+- **State Management**: Svelte's built-in reactive state system\r\n+\r\n+### Backend\r\n+- **Runtime**: Node.js with Express.js\r\n+- **Language**: TypeScript for type safety\r\n+- **API**: RESTful endpoints with proper error handling\r\n+- **Validation**: Input validation and sanitization\r\n+\r\n+### Database & Persistence\r\n+- **Database**: Redis for fast, in-memory data storage\r\n+- **Serialization**: JSON-based data persistence\r\n+- **Backup**: Automatic state saving on all mutations\r\n+\r\n+### Infrastructure\r\n+- **Containerization**: Docker & Docker Compose\r\n+- **Development**: Hot reload for both frontend and backend\r\n+- **Production**: Optimized builds with static file serving\r\n+\r\n+## ðŸ“ Project Structure\r\n+\r\n+```\r\n+giga-lan-manager/\r\n+â”œâ”€â”€ src/                          # Frontend Source\r\n+â”‚   â”œâ”€â”€ app.css                  # Global styles and Tailwind imports\r\n+â”‚   â”œâ”€â”€ App.svelte               # Main application router\r\n+â”‚   â”œâ”€â”€ Layout.svelte            # Navigation and layout wrapper\r\n+â”‚   â”œâ”€â”€ main.ts                  # Application entry point\r\n+â”‚   â”œâ”€â”€ lib/\r\n+â”‚   â”‚   â””â”€â”€ api.ts              # API client functions\r\n+â”‚   â””â”€â”€ pages/                   # Route components\r\n+â”‚       â”œâ”€â”€ TournamentList.svelte    # Tournament lobby\r\n+â”‚       â”œâ”€â”€ TournamentDashboard.svelte # Tournament overview\r\n+â”‚       â”œâ”€â”€ Groups.svelte        # Group stage management\r\n+â”‚       â””â”€â”€ Brackets.svelte      # Playoff bracket display\r\n+â”œâ”€â”€ server/                      # Backend Source\r\n+â”‚   â”œâ”€â”€ index.ts                # Express server setup\r\n+â”‚   â””â”€â”€ tournament.ts           # Tournament business logic\r\n+â”œâ”€â”€ public/                      # Static assets\r\n+â”œâ”€â”€ tests/                       # Test files\r\n+â”œâ”€â”€ docker-compose.yml          # Docker orchestration\r\n+â”œâ”€â”€ Dockerfile                  # Container build instructions\r\n+â”œâ”€â”€ package.json                # Dependencies and scripts\r\n+â”œâ”€â”€ tsconfig.json               # TypeScript configuration\r\n+â””â”€â”€ README.md                   # This file\r\n+```\r\n+\r\n+## ðŸŽ¯ Tournament Flow & Rules\r\n+\r\n+### 1. Registration Phase\r\n+- **Duration**: Unlimited time\r\n+- **Actions Allowed**:\r\n+  - Add/remove players\r\n+  - Edit player names\r\n+  - Edit tournament name\r\n+  - Edit group names\r\n+- **Minimum Players**: 4 players required to start\r\n+\r\n+### 2. Group Stage\r\n+- **Format**: Swiss-lite with randomized pods\r\n+- **Rounds**: 3 rounds total\r\n+- **Match Format**: 1v1 matches within each group\r\n+- **Scoring**:\r\n+  - Win: 3 points\r\n+  - Draw: 1 point\r\n+  - Loss: 0 points\r\n+- **Advancement**: Top players advance to playoffs\r\n+\r\n+### 3. Playoffs\r\n+- **Format**: Single-elimination bracket\r\n+- **Bracket Sizes**: 4, 6, or 8 players\r\n+- **Match Types**:\r\n+  - Quarterfinals (6+ players)\r\n+  - Semifinals\r\n+  - Finals\r\n+  - 3rd Place Match (consolation)\r\n+- **Advancement**: Click winner to advance to next round\r\n+\r\n+### 4. Completion\r\n+- **Trigger**: All playoff matches completed\r\n+- **Celebration**: Champion podium with trophy effects\r\n+- **History**: Full bracket and results remain viewable\r\n+\r\n+## ðŸš€ Getting Started\r\n+\r\n+### Prerequisites\r\n+- **Docker & Docker Compose** (recommended)\r\n+- **Node.js 18+** (for local development)\r\n+- **Git** (for cloning)\r\n+\r\n+### Quick Start with Docker (Recommended)\r\n+\r\n+1. **Clone the repository**:\r\n+   ```bash\r\n+   git clone https://github.com/yourusername/giga-lan-manager.git\r\n+   cd giga-lan-manager\r\n+   ```\r\n+\r\n+2. **Start the application**:\r\n+   ```bash\r\n+   docker-compose up --build\r\n+   ```\r\n+\r\n+3. **Open your browser**:\r\n+   - Navigate to [http://localhost:3000](http://localhost:3000)\r\n+   - Start creating tournaments!\r\n+\r\n+### Local Development Setup\r\n+\r\n+1. **Start Redis**:\r\n+   ```bash\r\n+   docker run -d -p 6379:6379 redis:alpine\r\n+   ```\r\n+\r\n+2. **Install dependencies**:\r\n+   ```bash\r\n+   npm install\r\n+   ```\r\n+\r\n+3. **Start development servers**:\r\n+   ```bash\r\n+   # Terminal 1: Backend\r\n+   npm run dev:server\r\n+\r\n+   # Terminal 2: Frontend\r\n+   npm run dev:client\r\n+   ```\r\n+\r\n+4. **Access the application**:\r\n+   - Frontend: [http://localhost:5173](http://localhost:5173)\r\n+   - Backend API: [http://localhost:3000](http://localhost:3000)\r\n+\r\n+## ðŸ“¡ API Documentation\r\n+\r\n+### Tournament Management\r\n+\r\n+#### `GET /api/tournaments`\r\n+Get list of all tournaments\r\n+```json\r\n+[\r\n+  {\r\n+    \"id\": \"tournament-uuid\",\r\n+    \"name\": \"Summer LAN 2024\",\r\n+    \"state\": \"registration\",\r\n+    \"playerCount\": 8\r\n+  }\r\n+]\r\n+```\r\n+\r\n+#### `POST /api/tournaments`\r\n+Create a new tournament\r\n+```json\r\n+// Request\r\n+{\r\n+  \"name\": \"Tournament Name\"\r\n+}\r\n+\r\n+// Response\r\n+{\r\n+  \"id\": \"tournament-uuid\",\r\n+  \"name\": \"Tournament Name\"\r\n+}\r\n+```\r\n+\r\n+#### `DELETE /api/tournament/:tournamentId`\r\n+Delete a tournament\r\n+\r\n+### Tournament Operations\r\n+\r\n+#### `GET /api/tournament/:tournamentId/state`\r\n+Get complete tournament state\r\n+```json\r\n+{\r\n+  \"id\": \"tournament-uuid\",\r\n+  \"name\": \"Tournament Name\",\r\n+  \"players\": [...],\r\n+  \"pods\": [...],\r\n+  \"matches\": [...],\r\n+  \"bracketMatches\": [...],\r\n+  \"state\": \"playoffs\"\r\n+}\r\n+```\r\n+\r\n+#### `POST /api/tournament/:tournamentId/players`\r\n+Add a player\r\n+```json\r\n+// Request\r\n+{\r\n+  \"name\": \"Player Name\"\r\n+}\r\n+\r\n+// Response\r\n+{\r\n+  \"id\": \"player-uuid\",\r\n+  \"name\": \"Player Name\",\r\n+  \"points\": 0,\r\n+  \"matchesPlayed\": 0,\r\n+  \"wins\": 0,\r\n+  \"draws\": 0,\r\n+  \"losses\": 0,\r\n+  \"scoreDifferential\": 0\r\n+}\r\n+```\r\n+\r\n+#### `PUT /api/tournament/:tournamentId/player/:playerId`\r\n+Update player name\r\n+```json\r\n+// Request\r\n+{\r\n+  \"name\": \"New Player Name\"\r\n+}\r\n+```\r\n+\r\n+#### `POST /api/tournament/:tournamentId/start`\r\n+Start the group stage (requires minimum 4 players)\r\n+\r\n+#### `POST /api/tournament/:tournamentId/match/:matchId`\r\n+Submit match results\r\n+```json\r\n+// Request\r\n+{\r\n+  \"results\": {\r\n+    \"player1-id\": { \"points\": 3 },\r\n+    \"player2-id\": { \"points\": 0 }\r\n+  }\r\n+}\r\n+```\r\n+\r\n+#### `POST /api/tournament/:tournamentId/brackets`\r\n+Generate playoff brackets (requires all group matches completed)\r\n+\r\n+#### `POST /api/tournament/:tournamentId/bracket-match/:matchId`\r\n+Advance bracket winner\r\n+```json\r\n+// Request\r\n+{\r\n+  \"winnerId\": \"player-uuid\"\r\n+}\r\n+```\r\n+\r\n+#### `PUT /api/tournament/:tournamentId/name`\r\n+Update tournament name\r\n+```json\r\n+// Request\r\n+{\r\n+  \"name\": \"New Tournament Name\"\r\n+}\r\n+```\r\n+\r\n+#### `PUT /api/tournament/:tournamentId/group/:podId/name`\r\n+Update group name\r\n+```json\r\n+// Request\r\n+{\r\n+  \"name\": \"New Group Name\"\r\n+}\r\n+```\r\n+\r\n+#### `POST /api/tournament/:tournamentId/group/:podId/reset`\r\n+Reset group match results\r\n+\r\n+#### `POST /api/tournament/:tournamentId/reset`\r\n+Reset entire tournament to registration state\r\n+\r\n+## ðŸŽ¨ Design System\r\n+\r\n+### Color Palette\r\n+- **Primary Background**: `space-900` to `space-800` gradient\r\n+- **Accent Colors**:\r\n+  - Cyber Green: `#00ff88` (success, wins)\r\n+  - Cyber Blue: `#00d4ff` (information, links)\r\n+  - Cyber Pink: `#ff0080` (accent, playoffs)\r\n+  - Gaming Text: `#e8eef5` (primary text)\r\n+\r\n+### Typography\r\n+- **Primary Font**: Inter (system-ui fallback)\r\n+- **Weights**: 400 (normal), 700 (bold), 900 (black)\r\n+- **Sizes**: Responsive scaling from mobile to desktop\r\n+\r\n+### Components\r\n+- **Glass Effect**: Backdrop blur with subtle borders\r\n+- **Card Entrance**: Smooth slide-in animations\r\n+- **Hover Effects**: Scale transforms and glow effects\r\n+- **Status Indicators**: Color-coded badges and rings\r\n+\r\n+## ðŸ”§ Development\r\n+\r\n+### Available Scripts\r\n+```bash\r\n+# Development\r\n+npm run dev              # Start both frontend and backend\r\n+npm run dev:client       # Frontend only (Vite)\r\n+npm run dev:server       # Backend only (ts-node)\r\n+\r\n+# Building\r\n+npm run build           # Build for production\r\n+npm run build:server    # Build backend only\r\n+\r\n+# Testing\r\n+npm test                # Run test suite\r\n+npm run test:watch      # Watch mode testing\r\n+\r\n+# Docker\r\n+docker-compose up       # Start all services\r\n+docker-compose down     # Stop all services\r\n+docker-compose logs     # View logs\r\n+```\r\n+\r\n+### Environment Variables\r\n+```bash\r\n+# Redis Configuration\r\n+REDIS_URL=redis://localhost:6379\r\n+\r\n+# Server Configuration\r\n+PORT=3000\r\n+NODE_ENV=development\r\n+```\r\n+\r\n+### Code Quality\r\n+- **TypeScript**: Strict type checking enabled\r\n+- **ESLint**: Code linting and formatting\r\n+- **Prettier**: Automatic code formatting\r\n+- **Testing**: Jest test framework\r\n+\r\n+## ðŸš¢ Deployment\r\n+\r\n+### Docker Production Build\r\n+```bash\r\n+# Build and run in production mode\r\n+docker-compose -f docker-compose.yml up --build -d\r\n+\r\n+# Scale the application\r\n+docker-compose up -d --scale app=3\r\n+```\r\n+\r\n+### Manual Deployment\r\n+1. **Build the application**:\r\n+   ```bash\r\n+   npm run build\r\n+   npm run build:server\r\n+   ```\r\n+\r\n+2. **Configure environment**:\r\n+   ```bash\r\n+   export REDIS_URL=redis://your-redis-instance:6379\r\n+   export NODE_ENV=production\r\n+   ```\r\n+\r\n+3. **Start the server**:\r\n+   ```bash\r\n+   npm start\r\n+   ```\r\n+\r\n+### Nginx Configuration (Example)\r\n+```nginx\r\n+server {\r\n+    listen 80;\r\n+    server_name your-domain.com;\r\n+\r\n+    location / {\r\n+        proxy_pass http://localhost:3000;\r\n+        proxy_set_header Host $host;\r\n+        proxy_set_header X-Real-IP $remote_addr;\r\n+    }\r\n+\r\n+    location /api {\r\n+        proxy_pass http://localhost:3000/api;\r\n+        proxy_set_header Host $host;\r\n+        proxy_set_header X-Real-IP $remote_addr;\r\n+    }\r\n+}\r\n+```\r\n+\r\n+## ðŸ¤ Contributing\r\n+\r\n+### Development Workflow\r\n+1. **Fork the repository**\r\n+2. **Create a feature branch**: `git checkout -b feature/your-feature`\r\n+3. **Make your changes** with proper TypeScript types\r\n+4. **Add tests** for new functionality\r\n+5. **Run the linter**: `npm run lint`\r\n+6. **Test your changes**: `npm test`\r\n+7. **Submit a pull request**\r\n+\r\n+### Code Standards\r\n+- **TypeScript**: Use strict typing and avoid `any` types\r\n+- **Svelte**: Follow Svelte 5 best practices with `$state` and `$derived`\r\n+- **Commits**: Use conventional commit format\r\n+- **Documentation**: Update README for new features\r\n+\r\n+### Testing\r\n+```bash\r\n+# Run all tests\r\n+npm test\r\n+\r\n+# Run specific test file\r\n+npm test -- tournament.test.ts\r\n+\r\n+# Run with coverage\r\n+npm run test:coverage\r\n+```\r\n+\r\n+## ðŸ“„ License\r\n+\r\n+This project is licensed under the MIT License - see the [LICENSE](LICENSE) file for details.\r\n+\r\n+## ðŸ™ Acknowledgments\r\n+\r\n+- **Svelte** for the amazing reactive framework\r\n+- **Tailwind CSS** for the utility-first styling approach\r\n+- **Redis** for reliable data persistence\r\n+- **Docker** for containerization excellence\r\n+\r\n+## ðŸ“ž Support\r\n+\r\n+- **Issues**: [GitHub Issues](https://github.com/yourusername/giga-lan-manager/issues)\r\n+- **Discussions**: [GitHub Discussions](https://github.com/yourusername/giga-lan-manager/discussions)\r\n+- **Documentation**: [Wiki](https://github.com/yourusername/giga-lan-manager/wiki)\r\n+\r\n+---\r\n+\r\n+**Made with â¤ï¸ for the LAN gaming community**\r\n"
                },
                {
                    "date": 1764023968101,
                    "content": "Index: \n===================================================================\n--- \n+++ \n@@ -1,12 +1,10 @@\n-# ðŸŽ® GIGA LAN Tournament Manager\r\n+# GIGA LAN Tournament Manager\r\n \r\n A modern, self-hosted web application for managing competitive LAN party tournaments with an immersive gaming aesthetic. Features a Swiss-lite group stage system and single-elimination playoffs with interactive bracket management.\r\n \r\n-![Tournament Manager Preview](https://via.placeholder.com/800x400/0a0e27/00ff88?text=GIGA+LAN+Tournament+Manager)\r\n+## Features\r\n \r\n-## âœ¨ Features\r\n-\r\n ### ðŸ† Tournament Management\r\n - **Multi-Tournament Support**: Create and manage multiple tournaments simultaneously\r\n - **Real-time State Management**: Live updates of tournament progress and standings\r\n - **Tournament Completion**: Automatic completion detection with celebration podium\r\n"
                },
                {
                    "date": 1764023978804,
                    "content": "Index: \n===================================================================\n--- \n+++ \n@@ -3,33 +3,33 @@\n A modern, self-hosted web application for managing competitive LAN party tournaments with an immersive gaming aesthetic. Features a Swiss-lite group stage system and single-elimination playoffs with interactive bracket management.\r\n \r\n ## Features\r\n \r\n-### ðŸ† Tournament Management\r\n+### Tournament Management\r\n - **Multi-Tournament Support**: Create and manage multiple tournaments simultaneously\r\n - **Real-time State Management**: Live updates of tournament progress and standings\r\n - **Tournament Completion**: Automatic completion detection with celebration podium\r\n \r\n-### ðŸ‘¥ Player Management\r\n+### Player Management\r\n - **Dynamic Registration**: Add players during registration phase\r\n - **Player Name Editing**: Edit player names throughout tournament (with restrictions)\r\n - **Live Standings**: Real-time player statistics and rankings\r\n \r\n-### ðŸŽ¯ Group Stage (Swiss-lite)\r\n+### Group Stage (Swiss-lite)\r\n - **Automated Pod Generation**: Smart grouping based on player count\r\n - **Round-Robin Matches**: Complete round-robin within each group\r\n - **Flexible Scoring**: Win (3pts), Draw (1pt), Loss (0pts)\r\n - **Group Name Customization**: Edit group names during registration\r\n - **Match Result Submission**: Interactive result entry with validation\r\n \r\n-### ðŸ… Playoffs & Brackets\r\n+### Playoffs & Brackets\r\n - **Single Elimination**: Traditional bracket format\r\n - **Interactive Advancement**: Click-to-advance bracket system\r\n - **Multiple Bracket Sizes**: 4, 6, or 8 player playoffs\r\n - **3rd Place Matches**: Consolation bracket for comprehensive placement\r\n - **Champion Celebration**: Immersive podium with trophy and confetti effects\r\n \r\n-### ðŸŽ¨ User Experience\r\n+### User Experience\r\n - **Gaming Aesthetic**: Cyberpunk-inspired dark theme with neon accents\r\n - **Responsive Design**: Works on desktop, tablet, and mobile devices\r\n - **Smooth Animations**: Card entrance effects and hover transitions\r\n - **Accessibility**: Keyboard navigation and screen reader support\r\n"
                },
                {
                    "date": 1764023994017,
                    "content": "Index: \n===================================================================\n--- \n+++ \n@@ -33,9 +33,9 @@\n - **Responsive Design**: Works on desktop, tablet, and mobile devices\r\n - **Smooth Animations**: Card entrance effects and hover transitions\r\n - **Accessibility**: Keyboard navigation and screen reader support\r\n \r\n-## ðŸ—ï¸ Architecture & Tech Stack\r\n+## Architecture & Tech Stack\r\n \r\n ### Frontend\r\n - **Framework**: Svelte 5 with modern reactivity (`$state`, `$derived`, `$effect`)\r\n - **Build Tool**: Vite for fast development and optimized production builds\r\n"
                },
                {
                    "date": 1764024250622,
                    "content": "Index: \n===================================================================\n--- \n+++ \n@@ -58,9 +58,9 @@\n - **Containerization**: Docker & Docker Compose\r\n - **Development**: Hot reload for both frontend and backend\r\n - **Production**: Optimized builds with static file serving\r\n \r\n-## ðŸ“ Project Structure\r\n+## Project Structure\r\n \r\n ```\r\n giga-lan-manager/\r\n â”œâ”€â”€ src/                          # Frontend Source\r\n@@ -86,9 +86,9 @@\n â”œâ”€â”€ tsconfig.json               # TypeScript configuration\r\n â””â”€â”€ README.md                   # This file\r\n ```\r\n \r\n-## ðŸŽ¯ Tournament Flow & Rules\r\n+## Tournament Flow & Rules\r\n \r\n ### 1. Registration Phase\r\n - **Duration**: Unlimited time\r\n - **Actions Allowed**:\r\n"
                },
                {
                    "date": 1764024259115,
                    "content": "Index: \n===================================================================\n--- \n+++ \n@@ -122,9 +122,9 @@\n - **Trigger**: All playoff matches completed\r\n - **Celebration**: Champion podium with trophy effects\r\n - **History**: Full bracket and results remain viewable\r\n \r\n-## ðŸš€ Getting Started\r\n+## Getting Started\r\n \r\n ### Prerequisites\r\n - **Docker & Docker Compose** (recommended)\r\n - **Node.js 18+** (for local development)\r\n@@ -171,9 +171,9 @@\n 4. **Access the application**:\r\n    - Frontend: [http://localhost:5173](http://localhost:5173)\r\n    - Backend API: [http://localhost:3000](http://localhost:3000)\r\n \r\n-## ðŸ“¡ API Documentation\r\n+## API Documentation\r\n \r\n ### Tournament Management\r\n \r\n #### `GET /api/tournaments`\r\n@@ -303,9 +303,9 @@\n \r\n #### `POST /api/tournament/:tournamentId/reset`\r\n Reset entire tournament to registration state\r\n \r\n-## ðŸŽ¨ Design System\r\n+## Design System\r\n \r\n ### Color Palette\r\n - **Primary Background**: `space-900` to `space-800` gradient\r\n - **Accent Colors**:\r\n@@ -324,9 +324,9 @@\n - **Card Entrance**: Smooth slide-in animations\r\n - **Hover Effects**: Scale transforms and glow effects\r\n - **Status Indicators**: Color-coded badges and rings\r\n \r\n-## ðŸ”§ Development\r\n+## Development\r\n \r\n ### Available Scripts\r\n ```bash\r\n # Development\r\n@@ -363,9 +363,9 @@\n - **ESLint**: Code linting and formatting\r\n - **Prettier**: Automatic code formatting\r\n - **Testing**: Jest test framework\r\n \r\n-## ðŸš¢ Deployment\r\n+## Deployment\r\n \r\n ### Docker Production Build\r\n ```bash\r\n # Build and run in production mode\r\n@@ -412,9 +412,9 @@\n     }\r\n }\r\n ```\r\n \r\n-## ðŸ¤ Contributing\r\n+## Contributing\r\n \r\n ### Development Workflow\r\n 1. **Fork the repository**\r\n 2. **Create a feature branch**: `git checkout -b feature/your-feature`\r\n@@ -441,24 +441,24 @@\n # Run with coverage\r\n npm run test:coverage\r\n ```\r\n \r\n-## ðŸ“„ License\r\n+## License\r\n \r\n This project is licensed under the MIT License - see the [LICENSE](LICENSE) file for details.\r\n \r\n-## ðŸ™ Acknowledgments\r\n+## Acknowledgments\r\n \r\n - **Svelte** for the amazing reactive framework\r\n - **Tailwind CSS** for the utility-first styling approach\r\n - **Redis** for reliable data persistence\r\n - **Docker** for containerization excellence\r\n \r\n-## ðŸ“ž Support\r\n+## Support\r\n \r\n - **Issues**: [GitHub Issues](https://github.com/yourusername/giga-lan-manager/issues)\r\n - **Discussions**: [GitHub Discussions](https://github.com/yourusername/giga-lan-manager/discussions)\r\n - **Documentation**: [Wiki](https://github.com/yourusername/giga-lan-manager/wiki)\r\n \r\n ---\r\n \r\n-**Made with â¤ï¸ for the LAN gaming community**\r\n+**Made with for the LAN gaming community**\r\n"
                }
            ],
            "date": 1763982588127,
            "name": "Commit-0",
            "content": "# Giga LAN Manager\r\n\r\n## Project Overview\r\nA self-hosted web application for managing LAN party tournaments with a Swiss-lite group stage and Double-House playoffs. Supports group phases, scoring, and interactive brackets.\r\n\r\n## Tech Stack\r\n- Frontend: Svelte (Vite) + Tailwind CSS\r\n- Backend: Node.js (Express) + TypeScript\r\n- Database: Redis\r\n- Infrastructure: Docker & Docker Compose\r\n\r\n## Folder Structure\r\n- `server/`: Backend logic, tournament management, API endpoints\r\n- `src/`: Frontend Svelte components, pages, API client\r\n- `public/`: Static assets\r\n- `tests/`: Test files (e.g., brackets.test.ts)\r\n- Root files: package.json, docker-compose.yml, vite.config.ts, etc.\r\n\r\n## Getting Started\r\nSee detailed instructions in this file or run with Docker: `docker compose up --build`\r\n\r\n## Usage\r\n1. Registration: Add players on home page\r\n2. Start Group Stage: Once >=4 players\r\n3. Groups: Enter points for matches\r\n4. Brackets: Generate and advance winners\r\n\r\n"
        }
    ]
}