{
    "sourceFile": "src/app.css",
    "activeCommit": 0,
    "commits": [
        {
            "activePatchIndex": 3,
            "patches": [
                {
                    "date": 1764025796993,
                    "content": "Index: \n===================================================================\n--- \n+++ \n"
                },
                {
                    "date": 1764027290417,
                    "content": "Index: \n===================================================================\n--- \n+++ \n@@ -109,4 +109,10 @@\n }\r\n \r\n /* Cropper.js styles */\r\n @import 'cropperjs/dist/cropper.css';\r\n+\r\n+/* Circular cropper overlay */\r\n+.cropper-circular .cropper-view-box,\r\n+.cropper-circular .cropper-face {\r\n+  border-radius: 50% !important;\r\n+}\n\\ No newline at end of file\n"
                },
                {
                    "date": 1764029980096,
                    "content": "Index: \n===================================================================\n--- \n+++ \n@@ -114,5 +114,9 @@\n /* Circular cropper overlay */\r\n .cropper-circular .cropper-view-box,\r\n .cropper-circular .cropper-face {\r\n   border-radius: 50% !important;\r\n+}\r\n+\r\n+.cropper-canvas img {\r\n+  display: none !important;\r\n }\n\\ No newline at end of file\n"
                },
                {
                    "date": 1764030417731,
                    "content": "Index: \n===================================================================\n--- \n+++ \n@@ -106,17 +106,4 @@\n   height: 100%;\r\n   pointer-events: none;\r\n   z-index: 9999;\r\n }\r\n-\r\n-/* Cropper.js styles */\r\n-@import 'cropperjs/dist/cropper.css';\r\n-\r\n-/* Circular cropper overlay */\r\n-.cropper-circular .cropper-view-box,\r\n-.cropper-circular .cropper-face {\r\n-  border-radius: 50% !important;\r\n-}\r\n-\r\n-.cropper-canvas img {\r\n-  display: none !important;\r\n-}\n\\ No newline at end of file\n"
                }
            ],
            "date": 1764025796993,
            "name": "Commit-0",
            "content": "@tailwind base;\r\n@tailwind components;\r\n@tailwind utilities;\r\n\r\n* {\r\n  margin: 0;\r\n  padding: 0;\r\n  box-sizing: border-box;\r\n}\r\n\r\n:root {\r\n  font-family: 'Inter', system-ui, Avenir, Helvetica, Arial, sans-serif;\r\n  line-height: 1.6;\r\n  font-weight: 400;\r\n  color: #e8eef5;\r\n  background: linear-gradient(135deg, #0a0e27 0%, #151937 100%);\r\n  min-height: 100vh;\r\n  font-synthesis: none;\r\n  text-rendering: optimizeLegibility;\r\n  -webkit-font-smoothing: antialiased;\r\n  -moz-osx-font-smoothing: grayscale;\r\n}\r\n\r\nbody {\r\n  margin: 0;\r\n  padding: 0;\r\n  overflow-x: hidden;\r\n}\r\n\r\n/* Scrollbar styling */\r\n::-webkit-scrollbar {\r\n  width: 10px;\r\n  height: 10px;\r\n}\r\n\r\n::-webkit-scrollbar-track {\r\n  background: #0a0e27;\r\n}\r\n\r\n::-webkit-scrollbar-thumb {\r\n  background: #2a3052;\r\n  border-radius: 5px;\r\n}\r\n\r\n::-webkit-scrollbar-thumb:hover {\r\n  background: #00ff88;\r\n}\r\n\r\n/* Glass morphism utility */\r\n.glass {\r\n  background: rgba(30, 36, 71, 0.7);\r\n  backdrop-filter: blur(10px);\r\n  border: 1px solid rgba(255, 255, 255, 0.1);\r\n}\r\n\r\n/* Gradient text */\r\n.gradient-text {\r\n  background: linear-gradient(135deg, #00ff88 0%, #00d4ff 100%);\r\n  -webkit-background-clip: text;\r\n  -webkit-text-fill-color: transparent;\r\n  background-clip: text;\r\n}\r\n\r\n/* Button hover effects */\r\n.btn-glow:hover {\r\n  box-shadow: 0 0 30px rgba(0, 255, 136, 0.6);\r\n  transform: translateY(-2px);\r\n}\r\n\r\n/* Card entrance animation */\r\n@keyframes cardEntrance {\r\n  from {\r\n    opacity: 0;\r\n    transform: translateY(20px) scale(0.95);\r\n  }\r\n  to {\r\n    opacity: 1;\r\n    transform: translateY(0) scale(1);\r\n  }\r\n}\r\n\r\n.card-entrance {\r\n  animation: cardEntrance 0.4s ease-out forwards;\r\n}\r\n\r\n/* Pulse animation for status indicators */\r\n@keyframes statusPulse {\r\n  0%, 100% {\r\n    opacity: 1;\r\n  }\r\n  50% {\r\n    opacity: 0.5;\r\n  }\r\n}\r\n\r\n.status-pulse {\r\n  animation: statusPulse 2s ease-in-out infinite;\r\n}\r\n\r\n/* Confetti effect (placeholder for JS-based confetti) */\r\n.confetti-container {\r\n  position: fixed;\r\n  top: 0;\r\n  left: 0;\r\n  width: 100%;\r\n  height: 100%;\r\n  pointer-events: none;\r\n  z-index: 9999;\r\n}\r\n\r\n/* Cropper.js styles */\r\n@import 'cropperjs/dist/cropper.css';\r\n"
        }
    ]
}